multicsv/__init__.py
multicsv/exceptions.py
multicsv/file.py
multicsv/open.py
multicsv/py.typed
multicsv/section.py
multicsv/subtextio.py
multicsv-1.0.5.dist-info/METADATA
multicsv-1.0.5.dist-info/WHEEL
multicsv-1.0.5.dist-info/licenses/COPYING
multicsv-1.0.5.dist-info/RECORD
