Metadata-Version: 2.4
Name: multicsv
Version: 1.0.5
Summary: A Python library for handling multi-CSV format.
Author-email: British Columbia Centre for Excellence in HIV/AIDS <vmysak@bccfe.ca>
License-Expression: GPL-3.0
License-File: COPYING
Provides-Extra: dev
Requires-Dist: bandit; extra == 'dev'
Requires-Dist: flake8; extra == 'dev'
Requires-Dist: mypy; extra == 'dev'
Provides-Extra: test
Requires-Dist: pytest-cov; extra == 'test'
Requires-Dist: pytest>=6.0; extra == 'test'
